codepipeline_wrapper/__init__.py
codepipeline_wrapper/function.py
codepipeline_wrapper-0.1.0.dist-info/LICENSE
codepipeline_wrapper-0.1.0.dist-info/WHEEL
codepipeline_wrapper-0.1.0.dist-info/METADATA
codepipeline_wrapper-0.1.0.dist-info/RECORD
